{
    "type": "AnnotationPage",
    "@context": [
        "http://www.w3.org/ns/anno.jsonld"
    ],
    "items": [
        {
            "id": "7.24.1",
            "@context": [
                "http://www.w3.org/ns/anno.jsonld",
                "http://geojson.org/geojson-ld/geojson-context.jsonld",
                "http://iiif.io/api/presentation/3/context.json"
            ],
            "type": "Annotation",
            "motivation": "georeferencing",
            "target": {
                "type": "Image",
                "source": "https://service.archief.nl/iip/e9/0b/05/9d/a5/ad/48/92/a2/51/a3/6a/13/5b/e5/16/418ebf07-7c80-476c-a3db-ae27ff69091a.jp2/full/full/0/default.jpg",
                "selector": {
                    "type": "SvgSelector",
                    "value": "<svg width=\"2506\" height=\"6059\"><polygon points=\"0,0 0,6059 2506,6059 2506,0\" /></svg>"
                },
                "service": [
                    {
                        "@id": "https://service.archief.nl/iip/e9/0b/05/9d/a5/ad/48/92/a2/51/a3/6a/13/5b/e5/16/418ebf07-7c80-476c-a3db-ae27ff69091a.jp2",
                        "type": "ImageService2"
                    }
                ]
            },
            "body": {
                "type": "FeatureCollection",
                "transformation": {
                    "type": "polynomial",
                    "options": {
                        "order": 1
                    }
                },
                "features": [
                    {
                        "type": "Feature",
                        "properties": {
                            "pixelCoords": [
                                1268.7088623046875,
                                3836.19921875
                            ]
                        },
                        "geometry": {
                            "type": "Point",
                            "coordinates": [
                                4.563099190450412,
                                52.4012137288059
                            ]
                        }
                    },
                    {
                        "type": "Feature",
                        "properties": {
                            "pixelCoords": [
                                1460.107666015625,
                                3849.323974609375
                            ]
                        },
                        "geometry": {
                            "type": "Point",
                            "coordinates": [
                                4.57072994977879,
                                52.40134901415516
                            ]
                        }
                    },
                    {
                        "type": "Feature",
                        "properties": {
                            "pixelCoords": [
                                1273.75634765625,
                                3792.60302734375
                            ]
                        },
                        "geometry": {
                            "type": "Point",
                            "coordinates": [
                                4.563206050591175,
                                52.402438066166326
                            ]
                        }
                    },
                    {
                        "type": "Feature",
                        "properties": {
                            "pixelCoords": [
                                1395.1673583984375,
                                3680.5830078125
                            ]
                        },
                        "geometry": {
                            "type": "Point",
                            "coordinates": [
                                4.568293522561836,
                                52.40543689892642
                            ]
                        }
                    },
                    {
                        "type": "Feature",
                        "properties": {
                            "pixelCoords": [
                                1278.664794921875,
                                3835.473388671875
                            ]
                        },
                        "geometry": {
                            "type": "Point",
                            "coordinates": [
                                4.563099190450412,
                                52.4012137288059
                            ]
                        }
                    },
                    {
                        "type": "Feature",
                        "properties": {
                            "pixelCoords": [
                                1809.01416015625,
                                4612.8720703125
                            ]
                        },
                        "geometry": {
                            "type": "Point",
                            "coordinates": [
                                4.582703391938649,
                                52.38343585008903
                            ]
                        }
                    },
                    {
                        "type": "Feature",
                        "properties": {
                            "pixelCoords": [
                                1159.754638671875,
                                3574.9765625
                            ]
                        },
                        "geometry": {
                            "type": "Point",
                            "coordinates": [
                                4.559217612146692,
                                52.407017233055825
                            ]
                        }
                    },
                    {
                        "type": "Feature",
                        "properties": {
                            "pixelCoords": [
                                1528.556640625,
                                3924.9384765625
                            ]
                        },
                        "geometry": {
                            "type": "Point",
                            "coordinates": [
                                4.57269507330763,
                                52.3995248303856
                            ]
                        }
                    },
                    {
                        "type": "Feature",
                        "properties": {
                            "pixelCoords": [
                                1403.59765625,
                                3796.154052734375
                            ]
                        },
                        "geometry": {
                            "type": "Point",
                            "coordinates": [
                                4.568891913156536,
                                52.40262546637439
                            ]
                        }
                    },
                    {
                        "type": "Feature",
                        "properties": {
                            "pixelCoords": [
                                1443.811767578125,
                                3793.8115234375
                            ]
                        },
                        "geometry": {
                            "type": "Point",
                            "coordinates": [
                                4.569487719388917,
                                52.40261866787004
                            ]
                        }
                    },
                    {
                        "type": "Feature",
                        "properties": {
                            "pixelCoords": [
                                1643.1312255859375,
                                3828.5009765625
                            ]
                        },
                        "geometry": {
                            "type": "Point",
                            "coordinates": [
                                4.577480831170584,
                                52.4025314572588
                            ]
                        }
                    },
                    {
                        "type": "Feature",
                        "properties": {
                            "pixelCoords": [
                                1467.127197265625,
                                3978.376220703125
                            ]
                        },
                        "geometry": {
                            "type": "Point",
                            "coordinates": [
                                4.571147532693864,
                                52.39816253855371
                            ]
                        }
                    },
                    {
                        "type": "Feature",
                        "properties": {
                            "pixelCoords": [
                                1546.024169921875,
                                4490.69091796875
                            ]
                        },
                        "geometry": {
                            "type": "Point",
                            "coordinates": [
                                4.57205138124137,
                                52.38610014914197
                            ]
                        }
                    },
                    {
                        "type": "Feature",
                        "properties": {
                            "pixelCoords": [
                                1378.007568359375,
                                3672.966552734375
                            ]
                        },
                        "geometry": {
                            "type": "Point",
                            "coordinates": [
                                4.568293522561836,
                                52.40543689892642
                            ]
                        }
                    },
                    {
                        "type": "Feature",
                        "properties": {
                            "pixelCoords": [
                                1432.8719482421875,
                                3755.76953125
                            ]
                        },
                        "geometry": {
                            "type": "Point",
                            "coordinates": [
                                4.569028051435011,
                                52.40340753487789
                            ]
                        }
                    },
                    {
                        "type": "Feature",
                        "properties": {
                            "pixelCoords": [
                                1554.6790771484375,
                                4105.16015625
                            ]
                        },
                        "geometry": {
                            "type": "Point",
                            "coordinates": [
                                4.573243231209453,
                                52.39510357321934
                            ]
                        }
                    },
                    {
                        "type": "Feature",
                        "properties": {
                            "pixelCoords": [
                                1176.0712890625,
                                3580.237060546875
                            ]
                        },
                        "geometry": {
                            "type": "Point",
                            "coordinates": [
                                4.559217612146692,
                                52.407017233055825
                            ]
                        }
                    },
                    {
                        "type": "Feature",
                        "properties": {
                            "pixelCoords": [
                                1840.6373291015625,
                                4267.06591796875
                            ]
                        },
                        "geometry": {
                            "type": "Point",
                            "coordinates": [
                                4.584350422727919,
                                52.391696837405895
                            ]
                        }
                    },
                    {
                        "type": "Feature",
                        "properties": {
                            "pixelCoords": [
                                1917.4036865234375,
                                4568.298828125
                            ]
                        },
                        "geometry": {
                            "type": "Point",
                            "coordinates": [
                                4.587732453978509,
                                52.38528339518299
                            ]
                        }
                    },
                    {
                        "type": "Feature",
                        "properties": {
                            "pixelCoords": [
                                1195.995361328125,
                                3867.222900390625
                            ]
                        },
                        "geometry": {
                            "type": "Point",
                            "coordinates": [
                                4.559936535338021,
                                52.40077522583994
                            ]
                        }
                    },
                    {
                        "type": "Feature",
                        "properties": {
                            "pixelCoords": [
                                1140.05712890625,
                                3720.031982421875
                            ]
                        },
                        "geometry": {
                            "type": "Point",
                            "coordinates": [
                                4.558940291441164,
                                52.40388839265646
                            ]
                        }
                    },
                    {
                        "type": "Feature",
                        "properties": {
                            "pixelCoords": [
                                1350.0360107421875,
                                3817.451904296875
                            ]
                        },
                        "geometry": {
                            "type": "Point",
                            "coordinates": [
                                4.566018722996382,
                                52.40137179219972
                            ]
                        }
                    },
                    {
                        "type": "Feature",
                        "properties": {
                            "pixelCoords": [
                                873.212890625,
                                3178.429443359375
                            ]
                        },
                        "geometry": {
                            "type": "Point",
                            "coordinates": [
                                4.548969819672091,
                                52.41671455304469
                            ]
                        }
                    },
                    {
                        "type": "Feature",
                        "properties": {
                            "pixelCoords": [
                                1492.6158447265625,
                                4157.25439453125
                            ]
                        },
                        "geometry": {
                            "type": "Point",
                            "coordinates": [
                                4.571985256831814,
                                52.394192522304714
                            ]
                        }
                    },
                    {
                        "type": "Feature",
                        "properties": {
                            "pixelCoords": [
                                1216.47021484375,
                                4682.33837890625
                            ]
                        },
                        "geometry": {
                            "type": "Point",
                            "coordinates": [
                                4.560159328106994,
                                52.38069251264253
                            ]
                        }
                    },
                    {
                        "type": "Feature",
                        "properties": {
                            "pixelCoords": [
                                1452.4638671875,
                                4774.00927734375
                            ]
                        },
                        "geometry": {
                            "type": "Point",
                            "coordinates": [
                                4.568458730929437,
                                52.37952072146003
                            ]
                        }
                    },
                    {
                        "type": "Feature",
                        "properties": {
                            "pixelCoords": [
                                1452.7359619140625,
                                3751.085693359375
                            ]
                        },
                        "geometry": {
                            "type": "Point",
                            "coordinates": [
                                4.570176462991129,
                                52.404277348175164
                            ]
                        }
                    },
                    {
                        "type": "Feature",
                        "properties": {
                            "pixelCoords": [
                                1544.9014892578125,
                                4171.87646484375
                            ]
                        },
                        "geometry": {
                            "type": "Point",
                            "coordinates": [
                                4.573089471119008,
                                52.394345078178
                            ]
                        }
                    },
                    {
                        "type": "Feature",
                        "properties": {
                            "pixelCoords": [
                                1400.9576416015625,
                                3810.999267578125
                            ]
                        },
                        "geometry": {
                            "type": "Point",
                            "coordinates": [
                                4.568891913156536,
                                52.40262546637439
                            ]
                        }
                    },
                    {
                        "type": "Feature",
                        "properties": {
                            "pixelCoords": [
                                1398.8714599609375,
                                3699.8427734375
                            ]
                        },
                        "geometry": {
                            "type": "Point",
                            "coordinates": [
                                4.568293522561836,
                                52.40543689892642
                            ]
                        }
                    }
                ]
            },
            "metadata": {
                "date": "1849",
                "handle": "http://hdl.handle.net/10648/b7e2c52b-057a-4cfe-a905-c63b04dfd8fe",
                "title": "Hillegom",
                "sheet": 24
            }
        }
    ]
}