{
    "type": "AnnotationPage",
    "@context": [
        "http://www.w3.org/ns/anno.jsonld"
    ],
    "items": [
        {
            "id": "7.31.8",
            "@context": [
                "http://www.w3.org/ns/anno.jsonld",
                "http://geojson.org/geojson-ld/geojson-context.jsonld",
                "http://iiif.io/api/presentation/3/context.json"
            ],
            "type": "Annotation",
            "motivation": "georeferencing",
            "target": {
                "type": "Image",
                "source": "https://service.archief.nl/iip/b8/fd/2d/71/4c/31/4a/c9/85/97/0b/d2/d5/5e/c7/61/0d86b9fd-2b2d-4dcf-8081-130fde968a26.jp2/full/full/0/default.jpg",
                "selector": {
                    "type": "SvgSelector",
                    "value": "<svg width=\"5021\" height=\"5940\"><polygon points=\"0,0 0,5940 5021,5940 5021,0\" /></svg>"
                },
                "service": [
                    {
                        "@id": "https://service.archief.nl/iip/b8/fd/2d/71/4c/31/4a/c9/85/97/0b/d2/d5/5e/c7/61/0d86b9fd-2b2d-4dcf-8081-130fde968a26.jp2",
                        "type": "ImageService2"
                    }
                ]
            },
            "body": {
                "type": "FeatureCollection",
                "transformation": {
                    "type": "polynomial",
                    "options": {
                        "order": 1
                    }
                },
                "features": [
                    {
                        "type": "Feature",
                        "properties": {
                            "pixelCoords": [
                                3704.58056640625,
                                4093.193359375
                            ]
                        },
                        "geometry": {
                            "type": "Point",
                            "coordinates": [
                                4.869879460624614,
                                52.1708163139097
                            ]
                        }
                    },
                    {
                        "type": "Feature",
                        "properties": {
                            "pixelCoords": [
                                2423.302001953125,
                                1212.5283203125
                            ]
                        },
                        "geometry": {
                            "type": "Point",
                            "coordinates": [
                                4.850752016261474,
                                52.19846755822421
                            ]
                        }
                    },
                    {
                        "type": "Feature",
                        "properties": {
                            "pixelCoords": [
                                1272.971923828125,
                                2353.354736328125
                            ]
                        },
                        "geometry": {
                            "type": "Point",
                            "coordinates": [
                                4.832261010214236,
                                52.18772381787714
                            ]
                        }
                    },
                    {
                        "type": "Feature",
                        "properties": {
                            "pixelCoords": [
                                3656.036865234375,
                                4226.61083984375
                            ]
                        },
                        "geometry": {
                            "type": "Point",
                            "coordinates": [
                                4.869007560487226,
                                52.16948263064183
                            ]
                        }
                    },
                    {
                        "type": "Feature",
                        "properties": {
                            "pixelCoords": [
                                1046.7447509765625,
                                1217.4400634765625
                            ]
                        },
                        "geometry": {
                            "type": "Point",
                            "coordinates": [
                                4.828870239977659,
                                52.19856415861776
                            ]
                        }
                    },
                    {
                        "type": "Feature",
                        "properties": {
                            "pixelCoords": [
                                936.7255859375,
                                1949.5728759765625
                            ]
                        },
                        "geometry": {
                            "type": "Point",
                            "coordinates": [
                                4.827043614548385,
                                52.19146173578719
                            ]
                        }
                    },
                    {
                        "type": "Feature",
                        "properties": {
                            "pixelCoords": [
                                3677.466796875,
                                3424.7958984375
                            ]
                        },
                        "geometry": {
                            "type": "Point",
                            "coordinates": [
                                4.869552859824862,
                                52.177174320033274
                            ]
                        }
                    },
                    {
                        "type": "Feature",
                        "properties": {
                            "pixelCoords": [
                                543.5179443359375,
                                3668.76953125
                            ]
                        },
                        "geometry": {
                            "type": "Point",
                            "coordinates": [
                                4.82009348295132,
                                52.17520639775788
                            ]
                        }
                    },
                    {
                        "type": "Feature",
                        "properties": {
                            "pixelCoords": [
                                2201.657470703125,
                                1142.127197265625
                            ]
                        },
                        "geometry": {
                            "type": "Point",
                            "coordinates": [
                                4.847311936710822,
                                52.1993335736792
                            ]
                        }
                    },
                    {
                        "type": "Feature",
                        "properties": {
                            "pixelCoords": [
                                1012.8768920898438,
                                1678.4532470703125
                            ]
                        },
                        "geometry": {
                            "type": "Point",
                            "coordinates": [
                                4.828307884006318,
                                52.19429202540381
                            ]
                        }
                    },
                    {
                        "type": "Feature",
                        "properties": {
                            "pixelCoords": [
                                3530.441162109375,
                                4325.263671875
                            ]
                        },
                        "geometry": {
                            "type": "Point",
                            "coordinates": [
                                4.867232189399588,
                                52.168482612008454
                            ]
                        }
                    },
                    {
                        "type": "Feature",
                        "properties": {
                            "pixelCoords": [
                                2373.421630859375,
                                5235.234375
                            ]
                        },
                        "geometry": {
                            "type": "Point",
                            "coordinates": [
                                4.8485715455179745,
                                52.159821827049605
                            ]
                        }
                    },
                    {
                        "type": "Feature",
                        "properties": {
                            "pixelCoords": [
                                2902.67578125,
                                3218.7744140625
                            ]
                        },
                        "geometry": {
                            "type": "Point",
                            "coordinates": [
                                4.857445079648557,
                                52.17912081619879
                            ]
                        }
                    },
                    {
                        "type": "Feature",
                        "properties": {
                            "pixelCoords": [
                                443.0648193359375,
                                668.5738525390625
                            ]
                        },
                        "geometry": {
                            "type": "Point",
                            "coordinates": [
                                4.819468891322674,
                                52.20383625559215
                            ]
                        }
                    },
                    {
                        "type": "Feature",
                        "properties": {
                            "pixelCoords": [
                                3848.1962890625,
                                3889.96337890625
                            ]
                        },
                        "geometry": {
                            "type": "Point",
                            "coordinates": [
                                4.872172858393584,
                                52.17288006429025
                            ]
                        }
                    },
                    {
                        "type": "Feature",
                        "properties": {
                            "pixelCoords": [
                                4479.8681640625,
                                1249.108154296875
                            ]
                        },
                        "geometry": {
                            "type": "Point",
                            "coordinates": [
                                4.882902081835541,
                                52.198075834567646
                            ]
                        }
                    },
                    {
                        "type": "Feature",
                        "properties": {
                            "pixelCoords": [
                                3817.90283203125,
                                3684.22802734375
                            ]
                        },
                        "geometry": {
                            "type": "Point",
                            "coordinates": [
                                4.871567678321124,
                                52.17471107177168
                            ]
                        }
                    },
                    {
                        "type": "Feature",
                        "properties": {
                            "pixelCoords": [
                                1342.755615234375,
                                5048.51953125
                            ]
                        },
                        "geometry": {
                            "type": "Point",
                            "coordinates": [
                                4.832105251897893,
                                52.16192465579748
                            ]
                        }
                    },
                    {
                        "type": "Feature",
                        "properties": {
                            "pixelCoords": [
                                3239.47216796875,
                                1674.5791015625
                            ]
                        },
                        "geometry": {
                            "type": "Point",
                            "coordinates": [
                                4.86366317098776,
                                52.19413358086642
                            ]
                        }
                    },
                    {
                        "type": "Feature",
                        "properties": {
                            "pixelCoords": [
                                3118.43505859375,
                                3771.617431640625
                            ]
                        },
                        "geometry": {
                            "type": "Point",
                            "coordinates": [
                                4.8609082984044,
                                52.174088526068225
                            ]
                        }
                    },
                    {
                        "type": "Feature",
                        "properties": {
                            "pixelCoords": [
                                724.0599975585938,
                                5093.01953125
                            ]
                        },
                        "geometry": {
                            "type": "Point",
                            "coordinates": [
                                4.822815181630951,
                                52.16155112394808
                            ]
                        }
                    },
                    {
                        "type": "Feature",
                        "properties": {
                            "pixelCoords": [
                                2672.2197265625,
                                3131.615966796875
                            ]
                        },
                        "geometry": {
                            "type": "Point",
                            "coordinates": [
                                4.854269317492792,
                                52.180134437999705
                            ]
                        }
                    },
                    {
                        "type": "Feature",
                        "properties": {
                            "pixelCoords": [
                                4129.892578125,
                                307.66143798828125
                            ]
                        },
                        "geometry": {
                            "type": "Point",
                            "coordinates": [
                                4.877778324722598,
                                52.207194435714186
                            ]
                        }
                    },
                    {
                        "type": "Feature",
                        "properties": {
                            "pixelCoords": [
                                1864.1556396484375,
                                4916.61572265625
                            ]
                        },
                        "geometry": {
                            "type": "Point",
                            "coordinates": [
                                4.840754207590921,
                                52.16321295076243
                            ]
                        }
                    },
                    {
                        "type": "Feature",
                        "properties": {
                            "pixelCoords": [
                                2760.01220703125,
                                714.0967407226562
                            ]
                        },
                        "geometry": {
                            "type": "Point",
                            "coordinates": [
                                4.8559072230426406,
                                52.203294111091054
                            ]
                        }
                    },
                    {
                        "type": "Feature",
                        "properties": {
                            "pixelCoords": [
                                3633.0888671875,
                                4219.4599609375
                            ]
                        },
                        "geometry": {
                            "type": "Point",
                            "coordinates": [
                                4.869007560487226,
                                52.16948263064183
                            ]
                        }
                    },
                    {
                        "type": "Feature",
                        "properties": {
                            "pixelCoords": [
                                593.7811279296875,
                                1035.990478515625
                            ]
                        },
                        "geometry": {
                            "type": "Point",
                            "coordinates": [
                                4.821671595455836,
                                52.20046539857029
                            ]
                        }
                    },
                    {
                        "type": "Feature",
                        "properties": {
                            "pixelCoords": [
                                1864.1759033203125,
                                4918.83251953125
                            ]
                        },
                        "geometry": {
                            "type": "Point",
                            "coordinates": [
                                4.840754207590921,
                                52.16321295076243
                            ]
                        }
                    },
                    {
                        "type": "Feature",
                        "properties": {
                            "pixelCoords": [
                                4187.23974609375,
                                4209.59033203125
                            ]
                        },
                        "geometry": {
                            "type": "Point",
                            "coordinates": [
                                4.8772991432943344,
                                52.16981952689286
                            ]
                        }
                    },
                    {
                        "type": "Feature",
                        "properties": {
                            "pixelCoords": [
                                1933.37890625,
                                4616.349609375
                            ]
                        },
                        "geometry": {
                            "type": "Point",
                            "coordinates": [
                                4.8421602434910564,
                                52.16590303407961
                            ]
                        }
                    }
                ]
            },
            "metadata": {
                "date": "1849",
                "handle": "http://hdl.handle.net/10648/fe44da99-c1a6-41e2-9a4c-5a6b6760064b",
                "title": "Utrecht",
                "sheet": 31
            }
        }
    ]
}